{
  "variants": {
    "facing=south": {
      "model": "more_everything:block/powercablestraight"
    },
    "facing=north": {
      "model": "more_everything:block/powercablestraight"
    },
    "facing=east": {
      "model": "more_everything:block/powercablestraight",
      "x": 90
    },
    "facing=west": {
      "model": "more_everything:block/powercablestraight",
      "x": 90
    },
    "facing=up": {
      "model": "more_everything:block/powercablestraight",
      "x": 90,
      "y": 90
    },
    "facing=down": {
      "model": "more_everything:block/powercablestraight",
      "x": 90,
      "y": 90
    }
  }
}